metorial_exceptions/__init__.py
metorial_exceptions/exceptions.py
metorial_exceptions-1.0.3.dist-info/METADATA
metorial_exceptions-1.0.3.dist-info/WHEEL
metorial_exceptions-1.0.3.dist-info/licenses/LICENSE
metorial_exceptions-1.0.3.dist-info/RECORD
